<annotation>
	<folder></folder>
	<filename>1030611863_jpg.rf.7edae200febe5a5160fede9478f3e591.jpg</filename>
	<path>1030611863_jpg.rf.7edae200febe5a5160fede9478f3e591.jpg</path>
	<source>
		<database>roboflow.ai</database>
	</source>
	<size>
		<width>1000</width>
		<height>541</height>
		<depth>3</depth>
	</size>
	<segmented>0</segmented>
	<object>
		<name>mask</name>
		<pose>Unspecified</pose>
		<truncated>0</truncated>
		<difficult>0</difficult>
		<occluded>0</occluded>
		<bndbox>
			<xmin>232</xmin>
			<xmax>248</xmax>
			<ymin>213</ymin>
			<ymax>236</ymax>
		</bndbox>
	</object>
	<object>
		<name>mask</name>
		<pose>Unspecified</pose>
		<truncated>0</truncated>
		<difficult>0</difficult>
		<occluded>0</occluded>
		<bndbox>
			<xmin>934</xmin>
			<xmax>963</xmax>
			<ymin>227</ymin>
			<ymax>263</ymax>
		</bndbox>
	</object>
	<object>
		<name>no-mask</name>
		<pose>Unspecified</pose>
		<truncated>0</truncated>
		<difficult>0</difficult>
		<occluded>0</occluded>
		<bndbox>
			<xmin>568</xmin>
			<xmax>596</xmax>
			<ymin>216</ymin>
			<ymax>248</ymax>
		</bndbox>
	</object>
	<object>
		<name>mask</name>
		<pose>Unspecified</pose>
		<truncated>0</truncated>
		<difficult>0</difficult>
		<occluded>0</occluded>
		<bndbox>
			<xmin>621</xmin>
			<xmax>688</xmax>
			<ymin>197</ymin>
			<ymax>288</ymax>
		</bndbox>
	</object>
	<object>
		<name>mask</name>
		<pose>Unspecified</pose>
		<truncated>0</truncated>
		<difficult>0</difficult>
		<occluded>0</occluded>
		<bndbox>
			<xmin>456</xmin>
			<xmax>533</xmax>
			<ymin>172</ymin>
			<ymax>277</ymax>
		</bndbox>
	</object>
	<object>
		<name>mask</name>
		<pose>Unspecified</pose>
		<truncated>0</truncated>
		<difficult>0</difficult>
		<occluded>0</occluded>
		<bndbox>
			<xmin>346</xmin>
			<xmax>419</xmax>
			<ymin>144</ymin>
			<ymax>235</ymax>
		</bndbox>
	</object>
	<object>
		<name>no-mask</name>
		<pose>Unspecified</pose>
		<truncated>0</truncated>
		<difficult>0</difficult>
		<occluded>0</occluded>
		<bndbox>
			<xmin>40</xmin>
			<xmax>72</xmax>
			<ymin>211</ymin>
			<ymax>252</ymax>
		</bndbox>
	</object>
	<object>
		<name>no-mask</name>
		<pose>Unspecified</pose>
		<truncated>0</truncated>
		<difficult>0</difficult>
		<occluded>0</occluded>
		<bndbox>
			<xmin>280</xmin>
			<xmax>312</xmax>
			<ymin>205</ymin>
			<ymax>245</ymax>
		</bndbox>
	</object>
</annotation>
